[{"date":"1684447200.0","open":"0.3678","high":"0.3718","low":"0.3668","close":"0.37","volume":"549.0"},{"date":"1684450800.0","open":"0.3699","high":"0.3713","low":"0.3689","close":"0.3706","volume":"413.0"},{"date":"1684454400.0","open":"0.3707","high":"0.3749","low":"0.3707","close":"0.3736","volume":"340.0"},{"date":"1684458000.0","open":"0.3737","high":"0.375","low":"0.3728","close":"0.374","volume":"423.0"},{"date":"1684461600.0","open":"0.3739","high":"0.3739","low":"0.3705","close":"0.3708","volume":"455.0"},{"date":"1684465200.0","open":"0.3709","high":"0.3722","low":"0.3701","close":"0.3716","volume":"406.0"},{"date":"1684468800.0","open":"0.3715","high":"0.372","low":"0.3697","close":"0.3701","volume":"439.0"},{"date":"1684472400.0","open":"0.37","high":"0.37","low":"0.3653","close":"0.3672","volume":"567.0"},{"date":"1684476000.0","open":"0.3673","high":"0.3695","low":"0.3667","close":"0.3685","volume":"291.0"},{"date":"1684479600.0","open":"0.3684","high":"0.3703","low":"0.3678","close":"0.3702","volume":"177.0"},{"date":"1684483200.0","open":"0.3701","high":"0.3707","low":"0.3695","close":"0.3699","volume":"239.0"},{"date":"1684486800.0","open":"0.37","high":"0.3708","low":"0.3698","close":"0.3702","volume":"295.0"},{"date":"1684490400.0","open":"0.3703","high":"0.3709","low":"0.3685","close":"0.3689","volume":"280.0"},{"date":"1684494000.0","open":"0.369","high":"0.3706","low":"0.3689","close":"0.3695","volume":"222.0"},{"date":"1684497600.0","open":"0.3696","high":"0.3699","low":"0.3686","close":"0.3693","volume":"227.0"},{"date":"1684501200.0","open":"0.3694","high":"0.3694","low":"0.368","close":"0.3686","volume":"218.0"},{"date":"1684504800.0","open":"0.3685","high":"0.369","low":"0.3676","close":"0.3681","volume":"245.0"},{"date":"1684508400.0","open":"0.3682","high":"0.3707","low":"0.3682","close":"0.3694","volume":"275.0"},{"date":"1684512000.0","open":"0.3695","high":"0.3699","low":"0.3684","close":"0.3688","volume":"310.0"},{"date":"1684515600.0","open":"0.3687","high":"0.3689","low":"0.3675","close":"0.3689","volume":"320.0"},{"date":"1684519200.0","open":"0.3688","high":"0.3725","low":"0.3666","close":"0.3689","volume":"1352.0"},{"date":"1684522800.0","open":"0.3688","high":"0.3696","low":"0.3676","close":"0.3681","volume":"404.0"},{"date":"1684526400.0","open":"0.368","high":"0.3701","low":"0.3676","close":"0.3692","volume":"289.0"},{"date":"1684530000.0","open":"0.3691","high":"0.3692","low":"0.3677","close":"0.3682","volume":"283.0"},{"date":"1684533600.0","open":"0.3681","high":"0.3681","low":"0.3652","close":"0.3672","volume":"381.0"},{"date":"1684537200.0","open":"0.3671","high":"0.3675","low":"0.3661","close":"0.3663","volume":"286.0"},{"date":"1684540800.0","open":"0.3672","high":"0.3677","low":"0.3666","close":"0.3677","volume":"134.0"},{"date":"1684544400.0","open":"0.3678","high":"0.3681","low":"0.3673","close":"0.3681","volume":"154.0"},{"date":"1684548000.0","open":"0.3682","high":"0.3682","low":"0.3668","close":"0.3673","volume":"227.0"},{"date":"1684551600.0","open":"0.3672","high":"0.3676","low":"0.3632","close":"0.3641","volume":"479.0"},{"date":"1684555200.0","open":"0.3642","high":"0.3653","low":"0.3629","close":"0.365","volume":"336.0"},{"date":"1684558800.0","open":"0.3649","high":"0.3653","low":"0.3632","close":"0.3638","volume":"251.0"},{"date":"1684562400.0","open":"0.3637","high":"0.3651","low":"0.3635","close":"0.3646","volume":"154.0"},{"date":"1684566000.0","open":"0.3645","high":"0.3649","low":"0.3641","close":"0.3648","volume":"178.0"},{"date":"1684569600.0","open":"0.3647","high":"0.3647","low":"0.3636","close":"0.364","volume":"176.0"},{"date":"1684573200.0","open":"0.3639","high":"0.364","low":"0.3632","close":"0.3636","volume":"177.0"},{"date":"1684576800.0","open":"0.3635","high":"0.3654","low":"0.3629","close":"0.3638","volume":"371.0"},{"date":"1684580400.0","open":"0.3639","high":"0.3648","low":"0.3635","close":"0.3648","volume":"159.0"},{"date":"1684584000.0","open":"0.3649","high":"0.3649","low":"0.3639","close":"0.3645","volume":"208.0"},{"date":"1684605600.0","open":"0.3648","high":"0.3656","low":"0.3646","close":"0.3651","volume":"292.0"},{"date":"1684609200.0","open":"0.365","high":"0.3652","low":"0.3634","close":"0.3636","volume":"168.0"},{"date":"1684612800.0","open":"0.3635","high":"0.3663","low":"0.3635","close":"0.366","volume":"253.0"},{"date":"1684616400.0","open":"0.3661","high":"0.3663","low":"0.3649","close":"0.3649","volume":"296.0"},{"date":"1684620000.0","open":"0.365","high":"0.3652","low":"0.3633","close":"0.3652","volume":"308.0"},{"date":"1684623600.0","open":"0.3651","high":"0.3652","low":"0.3642","close":"0.3643","volume":"159.0"},{"date":"1684630800.0","open":"0.3645","high":"0.3653","low":"0.3639","close":"0.3652","volume":"161.0"},{"date":"1684634400.0","open":"0.3651","high":"0.3657","low":"0.3648","close":"0.3656","volume":"151.0"},{"date":"1684638000.0","open":"0.3657","high":"0.3668","low":"0.3644","close":"0.3666","volume":"248.0"},{"date":"1684641600.0","open":"0.3667","high":"0.367","low":"0.3646","close":"0.3649","volume":"214.0"},{"date":"1684645200.0","open":"0.365","high":"0.3651","low":"0.3643","close":"0.3644","volume":"173.0"},{"date":"1684648800.0","open":"0.3643","high":"0.3647","low":"0.3638","close":"0.3647","volume":"108.0"},{"date":"1684652400.0","open":"0.3646","high":"0.3651","low":"0.364","close":"0.3647","volume":"167.0"},{"date":"1684656000.0","open":"0.3648","high":"0.3652","low":"0.3643","close":"0.3644","volume":"185.0"},{"date":"1684659600.0","open":"0.3645","high":"0.3646","low":"0.3639","close":"0.3646","volume":"159.0"},{"date":"1684663200.0","open":"0.3645","high":"0.3646","low":"0.3641","close":"0.3643","volume":"110.0"},{"date":"1684666800.0","open":"0.3642","high":"0.3645","low":"0.364","close":"0.3643","volume":"161.0"},{"date":"1684670400.0","open":"0.3641","high":"0.3644","low":"0.3638","close":"0.3641","volume":"196.0"},{"date":"1684674000.0","open":"0.3642","high":"0.3642","low":"0.3599","close":"0.3604","volume":"436.0"},{"date":"1684677600.0","open":"0.3603","high":"0.3613","low":"0.3595","close":"0.3605","volume":"437.0"},{"date":"1684681200.0","open":"0.3604","high":"0.3615","low":"0.3598","close":"0.3611","volume":"272.0"},{"date":"1684684800.0","open":"0.361","high":"0.3621","low":"0.3609","close":"0.3611","volume":"235.0"},{"date":"1684688400.0","open":"0.361","high":"0.3638","low":"0.361","close":"0.3618","volume":"308.0"},{"date":"1684692000.0","open":"0.3617","high":"0.3628","low":"0.3566","close":"0.3594","volume":"634.0"},{"date":"1684695600.0","open":"0.3593","high":"0.3599","low":"0.3575","close":"0.3584","volume":"407.0"},{"date":"1684699200.0","open":"0.3583","high":"0.3594","low":"0.3579","close":"0.3591","volume":"349.0"},{"date":"1684702800.0","open":"0.359","high":"0.3606","low":"0.3589","close":"0.3598","volume":"196.0"},{"date":"1684706400.0","open":"0.3599","high":"0.3605","low":"0.3596","close":"0.3601","volume":"169.0"},{"date":"1684710000.0","open":"0.3602","high":"0.3609","low":"0.3596","close":"0.3597","volume":"150.0"},{"date":"1684713600.0","open":"0.356","high":"0.3596","low":"0.3559","close":"0.3594","volume":"336.0"},{"date":"1684717200.0","open":"0.3593","high":"0.3604","low":"0.359","close":"0.36","volume":"150.0"},{"date":"1684720800.0","open":"0.3601","high":"0.3607","low":"0.359","close":"0.3596","volume":"108.0"},{"date":"1684724400.0","open":"0.3595","high":"0.3608","low":"0.3554","close":"0.3578","volume":"631.0"},{"date":"1684728000.0","open":"0.3577","high":"0.3595","low":"0.357","close":"0.3579","volume":"402.0"},{"date":"1684731600.0","open":"0.3578","high":"0.3613","low":"0.3575","close":"0.3609","volume":"221.0"},{"date":"1684735200.0","open":"0.361","high":"0.361","low":"0.3595","close":"0.36","volume":"186.0"},{"date":"1684738800.0","open":"0.3601","high":"0.3623","low":"0.3593","close":"0.3618","volume":"182.0"},{"date":"1684742400.0","open":"0.3619","high":"0.3624","low":"0.3609","close":"0.3613","volume":"194.0"},{"date":"1684746000.0","open":"0.3614","high":"0.3637","low":"0.361","close":"0.3628","volume":"252.0"},{"date":"1684749600.0","open":"0.3629","high":"0.3633","low":"0.3623","close":"0.3623","volume":"150.0"},{"date":"1684753200.0","open":"0.3624","high":"0.3664","low":"0.3615","close":"0.3659","volume":"389.0"},{"date":"1684756800.0","open":"0.3657","high":"0.3735","low":"0.3657","close":"0.3683","volume":"1275.0"},{"date":"1684760400.0","open":"0.3685","high":"0.3692","low":"0.3672","close":"0.3683","volume":"390.0"},{"date":"1684764000.0","open":"0.3681","high":"0.3685","low":"0.3661","close":"0.3677","volume":"284.0"},{"date":"1684767600.0","open":"0.3676","high":"0.3684","low":"0.3661","close":"0.3661","volume":"363.0"},{"date":"1684771200.0","open":"0.3662","high":"0.3694","low":"0.3657","close":"0.3683","volume":"535.0"},{"date":"1684774800.0","open":"0.3684","high":"0.369","low":"0.366","close":"0.3671","volume":"496.0"},{"date":"1684778400.0","open":"0.3672","high":"0.3675","low":"0.3659","close":"0.3667","volume":"312.0"},{"date":"1684782000.0","open":"0.3666","high":"0.3687","low":"0.3665","close":"0.3675","volume":"229.0"},{"date":"1684785600.0","open":"0.3676","high":"0.3681","low":"0.3664","close":"0.367","volume":"258.0"},{"date":"1684789200.0","open":"0.3671","high":"0.3686","low":"0.367","close":"0.3677","volume":"202.0"},{"date":"1684792800.0","open":"0.3678","high":"0.3685","low":"0.3672","close":"0.3677","volume":"285.0"},{"date":"1684796400.0","open":"0.3678","high":"0.3701","low":"0.3674","close":"0.3697","volume":"212.0"},{"date":"1684800000.0","open":"0.3691","high":"0.3695","low":"0.3681","close":"0.3688","volume":"180.0"},{"date":"1684803600.0","open":"0.3687","high":"0.3693","low":"0.367","close":"0.3672","volume":"316.0"},{"date":"1684807200.0","open":"0.3673","high":"0.3679","low":"0.3666","close":"0.3673","volume":"211.0"},{"date":"1684810800.0","open":"0.3674","high":"0.3679","low":"0.3651","close":"0.3657","volume":"357.0"},{"date":"1684814400.0","open":"0.3656","high":"0.3693","low":"0.3653","close":"0.3681","volume":"471.0"},{"date":"1684818000.0","open":"0.368","high":"0.3691","low":"0.3675","close":"0.3687","volume":"255.0"},{"date":"1684821600.0","open":"0.3688","high":"0.3749","low":"0.3684","close":"0.3733","volume":"766.0"},{"date":"1684825200.0","open":"0.3734","high":"0.3741","low":"0.3706","close":"0.3711","volume":"361.0"},{"date":"1684828800.0","open":"0.3712","high":"0.372","low":"0.3701","close":"0.3706","volume":"246.0"},{"date":"1684832400.0","open":"0.3707","high":"0.3716","low":"0.3691","close":"0.3696","volume":"265.0"},{"date":"1684836000.0","open":"0.3697","high":"0.3704","low":"0.3688","close":"0.3702","volume":"377.0"},{"date":"1684839600.0","open":"0.3703","high":"0.3703","low":"0.3685","close":"0.369","volume":"231.0"},{"date":"1684843200.0","open":"0.3691","high":"0.3695","low":"0.3683","close":"0.3688","volume":"255.0"},{"date":"1684846800.0","open":"0.3687","high":"0.3699","low":"0.3687","close":"0.3696","volume":"221.0"},{"date":"1684850400.0","open":"0.3697","high":"0.3705","low":"0.3696","close":"0.37","volume":"155.0"},{"date":"1684854000.0","open":"0.3701","high":"0.3706","low":"0.3693","close":"0.3696","volume":"246.0"},{"date":"1684857600.0","open":"0.3697","high":"0.3704","low":"0.3683","close":"0.3691","volume":"439.0"},{"date":"1684861200.0","open":"0.369","high":"0.3711","low":"0.3687","close":"0.37","volume":"307.0"},{"date":"1684864800.0","open":"0.3701","high":"0.3705","low":"0.3693","close":"0.3703","volume":"197.0"},{"date":"1684868400.0","open":"0.3704","high":"0.3705","low":"0.369","close":"0.3694","volume":"238.0"},{"date":"1684872000.0","open":"0.3695","high":"0.37","low":"0.3689","close":"0.3693","volume":"206.0"},{"date":"1684875600.0","open":"0.3692","high":"0.3697","low":"0.3681","close":"0.3692","volume":"283.0"},{"date":"1684879200.0","open":"0.3691","high":"0.3714","low":"0.3686","close":"0.3707","volume":"269.0"},{"date":"1684882800.0","open":"0.3708","high":"0.372","low":"0.3698","close":"0.3709","volume":"243.0"},{"date":"1684886400.0","open":"0.3703","high":"0.3708","low":"0.3697","close":"0.37","volume":"200.0"},{"date":"1684890000.0","open":"0.3701","high":"0.3708","low":"0.3694","close":"0.3699","volume":"151.0"},{"date":"1684893600.0","open":"0.3698","high":"0.3702","low":"0.3694","close":"0.3697","volume":"151.0"},{"date":"1684897200.0","open":"0.3696","high":"0.3699","low":"0.3677","close":"0.3684","volume":"281.0"},{"date":"1684900800.0","open":"0.3683","high":"0.3688","low":"0.3671","close":"0.3671","volume":"286.0"},{"date":"1684904400.0","open":"0.3672","high":"0.3686","low":"0.3669","close":"0.3684","volume":"184.0"},{"date":"1684908000.0","open":"0.3683","high":"0.3684","low":"0.3611","close":"0.3627","volume":"974.0"},{"date":"1684911600.0","open":"0.3626","high":"0.3643","low":"0.3614","close":"0.3641","volume":"479.0"},{"date":"1684915200.0","open":"0.364","high":"0.3644","low":"0.3635","close":"0.3642","volume":"241.0"},{"date":"1684918800.0","open":"0.3641","high":"0.3656","low":"0.3629","close":"0.3656","volume":"462.0"},{"date":"1684922400.0","open":"0.3657","high":"0.368","low":"0.3637","close":"0.3656","volume":"675.0"},{"date":"1684926000.0","open":"0.3657","high":"0.3665","low":"0.3653","close":"0.3658","volume":"352.0"},{"date":"1684929600.0","open":"0.3657","high":"0.3686","low":"0.3656","close":"0.3669","volume":"333.0"},{"date":"1684933200.0","open":"0.3668","high":"0.3672","low":"0.3649","close":"0.365","volume":"311.0"},{"date":"1684936800.0","open":"0.3651","high":"0.3656","low":"0.364","close":"0.3648","volume":"301.0"},{"date":"1684940400.0","open":"0.3646","high":"0.3655","low":"0.3638","close":"0.3642","volume":"266.0"},{"date":"1684944000.0","open":"0.3641","high":"0.365","low":"0.36","close":"0.3626","volume":"1022.0"},{"date":"1684947600.0","open":"0.3625","high":"0.3635","low":"0.3603","close":"0.3616","volume":"831.0"},{"date":"1684951200.0","open":"0.3615","high":"0.3628","low":"0.3597","close":"0.3612","volume":"667.0"},{"date":"1684954800.0","open":"0.3613","high":"0.3616","low":"0.3599","close":"0.361","volume":"329.0"},{"date":"1684958400.0","open":"0.3609","high":"0.3628","low":"0.3599","close":"0.3621","volume":"323.0"},{"date":"1684962000.0","open":"0.362","high":"0.3628","low":"0.3611","close":"0.3617","volume":"284.0"},{"date":"1684965600.0","open":"0.3616","high":"0.3636","low":"0.3614","close":"0.3629","volume":"273.0"},{"date":"1684969200.0","open":"0.363","high":"0.3645","low":"0.3624","close":"0.3641","volume":"316.0"},{"date":"1684972800.0","open":"0.3642","high":"0.3649","low":"0.3628","close":"0.3632","volume":"149.0"},{"date":"1684976400.0","open":"0.3633","high":"0.3642","low":"0.3626","close":"0.3632","volume":"162.0"},{"date":"1684980000.0","open":"0.3633","high":"0.364","low":"0.3632","close":"0.3633","volume":"190.0"},{"date":"1684983600.0","open":"0.3634","high":"0.3642","low":"0.3599","close":"0.3603","volume":"369.0"},{"date":"1684987200.0","open":"0.3602","high":"0.3614","low":"0.3542","close":"0.3564","volume":"1104.0"},{"date":"1684990800.0","open":"0.3565","high":"0.3585","low":"0.3561","close":"0.3585","volume":"280.0"},{"date":"1684994400.0","open":"0.3584","high":"0.3601","low":"0.3583","close":"0.3599","volume":"167.0"},{"date":"1684998000.0","open":"0.36","high":"0.3609","low":"0.3595","close":"0.3596","volume":"210.0"},{"date":"1685001600.0","open":"0.3597","high":"0.3599","low":"0.3586","close":"0.3591","volume":"202.0"},{"date":"1685005200.0","open":"0.3592","high":"0.3598","low":"0.3553","close":"0.3561","volume":"433.0"},{"date":"1685008800.0","open":"0.3562","high":"0.3564","low":"0.3552","close":"0.3558","volume":"278.0"},{"date":"1685012400.0","open":"0.3557","high":"0.3571","low":"0.3557","close":"0.357","volume":"236.0"},{"date":"1685016000.0","open":"0.3569","high":"0.3577","low":"0.3568","close":"0.3573","volume":"214.0"},{"date":"1685019600.0","open":"0.3574","high":"0.3577","low":"0.357","close":"0.3576","volume":"156.0"},{"date":"1685023200.0","open":"0.3577","high":"0.3577","low":"0.3559","close":"0.3575","volume":"244.0"},{"date":"1685026800.0","open":"0.3576","high":"0.3596","low":"0.3574","close":"0.358","volume":"410.0"},{"date":"1685030400.0","open":"0.3579","high":"0.3589","low":"0.3562","close":"0.3572","volume":"330.0"},{"date":"1685034000.0","open":"0.3573","high":"0.3581","low":"0.3564","close":"0.3573","volume":"298.0"},{"date":"1685037600.0","open":"0.3574","high":"0.3581","low":"0.3549","close":"0.3556","volume":"349.0"},{"date":"1685041200.0","open":"0.3557","high":"0.356","low":"0.3547","close":"0.3555","volume":"305.0"},{"date":"1685044800.0","open":"0.3556","high":"0.3564","low":"0.3543","close":"0.3562","volume":"260.0"},{"date":"1685048400.0","open":"0.3563","high":"0.3566","low":"0.3557","close":"0.3559","volume":"220.0"},{"date":"1685052000.0","open":"0.3558","high":"0.3606","low":"0.3558","close":"0.3577","volume":"741.0"},{"date":"1685055600.0","open":"0.3576","high":"0.3588","low":"0.3571","close":"0.3584","volume":"225.0"},{"date":"1685059200.0","open":"0.3579","high":"0.358","low":"0.3565","close":"0.3572","volume":"131.0"},{"date":"1685062800.0","open":"0.3571","high":"0.358","low":"0.3567","close":"0.3575","volume":"193.0"},{"date":"1685066400.0","open":"0.3576","high":"0.3585","low":"0.3571","close":"0.3574","volume":"176.0"},{"date":"1685070000.0","open":"0.3575","high":"0.358","low":"0.356","close":"0.3566","volume":"305.0"},{"date":"1685073600.0","open":"0.3565","high":"0.3578","low":"0.3529","close":"0.3544","volume":"463.0"},{"date":"1685077200.0","open":"0.3543","high":"0.3548","low":"0.3532","close":"0.3546","volume":"196.0"},{"date":"1685080800.0","open":"0.3547","high":"0.3562","low":"0.3544","close":"0.3558","volume":"171.0"},{"date":"1685084400.0","open":"0.3557","high":"0.3573","low":"0.3554","close":"0.3561","volume":"215.0"},{"date":"1685088000.0","open":"0.3562","high":"0.3564","low":"0.3545","close":"0.3551","volume":"238.0"},{"date":"1685091600.0","open":"0.3552","high":"0.3574","low":"0.3545","close":"0.3574","volume":"238.0"},{"date":"1685095200.0","open":"0.3573","high":"0.3578","low":"0.3567","close":"0.3577","volume":"273.0"},{"date":"1685098800.0","open":"0.3576","high":"0.3579","low":"0.357","close":"0.3574","volume":"189.0"},{"date":"1685102400.0","open":"0.3575","high":"0.3575","low":"0.3567","close":"0.3571","volume":"204.0"},{"date":"1685106000.0","open":"0.357","high":"0.357","low":"0.3559","close":"0.3564","volume":"143.0"},{"date":"1685109600.0","open":"0.3565","high":"0.3568","low":"0.3557","close":"0.3565","volume":"182.0"},{"date":"1685113200.0","open":"0.3564","high":"0.3576","low":"0.3551","close":"0.3565","volume":"481.0"},{"date":"1685116800.0","open":"0.3566","high":"0.3589","low":"0.3565","close":"0.3579","volume":"342.0"},{"date":"1685120400.0","open":"0.358","high":"0.3614","low":"0.358","close":"0.3598","volume":"523.0"},{"date":"1685124000.0","open":"0.3599","high":"0.361","low":"0.3592","close":"0.3597","volume":"303.0"},{"date":"1685127600.0","open":"0.3596","high":"0.3598","low":"0.3586","close":"0.3588","volume":"208.0"},{"date":"1685131200.0","open":"0.3589","high":"0.3592","low":"0.3579","close":"0.3581","volume":"195.0"},{"date":"1685134800.0","open":"0.3582","high":"0.3663","low":"0.3577","close":"0.365","volume":"928.0"},{"date":"1685138400.0","open":"0.3648","high":"0.3649","low":"0.3628","close":"0.3636","volume":"317.0"},{"date":"1685142000.0","open":"0.3637","high":"0.3652","low":"0.3633","close":"0.3644","volume":"206.0"},{"date":"1685145600.0","open":"0.3643","high":"0.3643","low":"0.3629","close":"0.3633","volume":"151.0"},{"date":"1685149200.0","open":"0.3634","high":"0.3638","low":"0.3618","close":"0.3619","volume":"195.0"},{"date":"1685152800.0","open":"0.3617","high":"0.3624","low":"0.3617","close":"0.362","volume":"169.0"},{"date":"1685156400.0","open":"0.3619","high":"0.3623","low":"0.3609","close":"0.3621","volume":"212.0"},{"date":"1685160000.0","open":"0.3622","high":"0.3634","low":"0.3617","close":"0.3633","volume":"162.0"},{"date":"1685163600.0","open":"0.3634","high":"0.3635","low":"0.3625","close":"0.3633","volume":"168.0"},{"date":"1685167200.0","open":"0.3631","high":"0.3664","low":"0.3626","close":"0.3653","volume":"306.0"},{"date":"1685170800.0","open":"0.3652","high":"0.3658","low":"0.3638","close":"0.3653","volume":"196.0"},{"date":"1685174400.0","open":"0.3654","high":"0.3654","low":"0.3637","close":"0.3637","volume":"180.0"},{"date":"1685178000.0","open":"0.3638","high":"0.3641","low":"0.3633","close":"0.3638","volume":"210.0"},{"date":"1685181600.0","open":"0.3637","high":"0.3637","low":"0.3627","close":"0.3634","volume":"162.0"},{"date":"1685185200.0","open":"0.3633","high":"0.3635","low":"0.3618","close":"0.3623","volume":"208.0"},{"date":"1685188800.0","open":"0.3624","high":"0.3632","low":"0.3624","close":"0.3628","volume":"56.0"}]